{
  "request_id":"lane3_to_lane4_current_workflow_model_refs_visibility_recheck_20260704_165000",
  "created_at_utc":"2026-07-04T16:50:00Z",
  "from_lane":"Lane_3",
  "to_lane":"Lane_4",
  "priority":"high",
  "purpose":"Follow-up clarification of current workflow runtime-gap check for the 9 refs previously reported.",
  "scope":{
    "workflow_path":"C:\\Comfy_UI\\Implementation\\workflows\\ui\\WAVE42_MAIN_FLOW_20260702.json",
    "workflow_sha256":"5C67A23D1F70A6E7A5687E99E58F73EA475A172B4736F32D192AB3929BC35EC9",
    "evidence_path":"C:\\Comfy_UI_Lora\\5_session_worktrees\\Lane_3\\Lane_3\\evidence\\20260704_165000_workflow_missing_refs_runtime_visibility_check_evidence.json",
    "unresolved_in_runtime":["/home/ubuntu/ComfyUI/models/ultralytics/bbox/hand_yolov8n.pt","bbox/hand_yolov8n.pt","dw-ll_ucoco_384_bs5.torchscript.pt","sam_vit_b_01ec64.pth"],
    "present_only_in_downloads":["C:\\Comfy_UI_Lora\\downloads\\Hands\\Better hands flux v1.0.safetensors","C:\\Comfy_UI_Lora\\downloads\\Hands\\Detailed_Hands-000001.safetensors","C:\\Comfy_UI_Lora\\downloads\\Hands\\feminine_hands.safetensors","C:\\Comfy_UI_Lora\\downloads\\Hands\\Hand v2.safetensors","C:\\Comfy_UI_Lora\\downloads\\Hands\\Hands.safetensors"]
  },
  "next_action":"Need explicit runtime mapping or install action for unresolved_in_runtime refs; downloads-only refs do not satisfy runtime visibility until placed under Runtime_Data or referenced by runtime path."
}
